sdenet/__init__.py
sdenet/eval/__init__.py
sdenet/eval/calculate_log.py
sdenet/eval/eval_detection.py
sdenet/models/__init__.py
sdenet/models/helpers.py
sdenet/models/resnet.py
sdenet/models/sdenet.py
sdenet/train/__init__.py
sdenet/train/resnet_train.py
sdenet/train/sdenet_train.py
sdenet-1.0.dist-info/LICENSE
sdenet-1.0.dist-info/METADATA
sdenet-1.0.dist-info/WHEEL
sdenet-1.0.dist-info/top_level.txt
sdenet-1.0.dist-info/RECORD
