Metadata-Version: 2.1
Name: sdenet
Version: 1.0
Summary: UNKNOWN
Home-page: UNKNOWN
Author: Philippe Remy
License: MIT
Platform: UNKNOWN
Requires-Python: >=3
Requires-Dist: numpy (==1.19.1)
Requires-Dist: tensorflow (==2.3.0)
Requires-Dist: tensorflow-addons (==0.11.2)
